zds_schema/__init__.py
zds_schema/admin.py
zds_schema/apps.py
zds_schema/constants.py
zds_schema/decorators.py
zds_schema/descriptors.py
zds_schema/exception_handling.py
zds_schema/exceptions.py
zds_schema/fields.py
zds_schema/filters.py
zds_schema/filtersets.py
zds_schema/geo.py
zds_schema/middleware.py
zds_schema/mocks.py
zds_schema/models.py
zds_schema/oas.py
zds_schema/permissions.py
zds_schema/routers.py
zds_schema/schema.py
zds_schema/scopes.py
zds_schema/search.py
zds_schema/serializers.py
zds_schema/tests.py
zds_schema/urls.py
zds_schema/utils.py
zds_schema/validators.py
zds_schema/version.py
zds_schema/views.py
zds_schema/viewsets.py
zds_schema/api/__init__.py
zds_schema/api/serializers.py
zds_schema/api/urls.py
zds_schema/api/views.py
zds_schema/conf/__init__.py
zds_schema/conf/api.py
zds_schema/inspectors/__init__.py
zds_schema/inspectors/files.py
zds_schema/inspectors/geojson.py
zds_schema/inspectors/query.py
zds_schema/inspectors/view.py
zds_schema/management/__init__.py
zds_schema/management/commands/__init__.py
zds_schema/management/commands/generate_swagger.py
zds_schema/management/commands/patch_error_contenttypes.py
zds_schema/migrations/0001_initial.py
zds_schema/migrations/0002_apicredential.py
zds_schema/migrations/__init__.py
zds_schema/templates/zds_schema/api_schema_to_markdown_table.html
zds_schema/templates/zds_schema/api_schema_to_markdown_table.md
zds_schema/templates/zds_schema/error_detail.html
zds_schema/templates/zds_schema/scopes.html
zds_schema/templatetags/__init__.py
zds_schema/templatetags/zds_schema.py
zds_schema/tests/__init__.py
zds_schema/tests/auth.py
zds_schema/tests/schema.py
zds_schema/tests/urls.py
zds_schema-0.22.0.data/scripts/generate_schema
zds_schema-0.22.0.data/scripts/generate_schema.cmd
zds_schema-0.22.0.data/scripts/patch_content_types
zds_schema-0.22.0.data/scripts/patch_content_types.cmd
zds_schema-0.22.0.dist-info/METADATA
zds_schema-0.22.0.dist-info/RECORD
zds_schema-0.22.0.dist-info/WHEEL
zds_schema-0.22.0.dist-info/top_level.txt
