Metadata-Version: 2.1
Name: zds-schema
Version: 0.22.0
Summary: Schema-generatie tooling
Home-page: https://github.com/VNG-Realisatie/gemma-zaken-common
Author: Maykin Media, VNG-Realisatie
Author-email: support@maykinmedia.nl
License: EUPL 1.2
Keywords: openapi,swagger,django,vng
Platform: UNKNOWN
Classifier: Development Status :: 3 - Alpha
Classifier: Framework :: Django
Classifier: Framework :: Django :: 2.0
Classifier: Intended Audience :: Developers
Classifier: Operating System :: Unix
Classifier: Operating System :: MacOS
Classifier: Operating System :: Microsoft :: Windows
Classifier: Programming Language :: Python :: 3.6
Classifier: Topic :: Software Development :: Libraries :: Python Modules
Provides-Extra: coverage
Provides-Extra: release
Provides-Extra: pep8
Provides-Extra: docs
Provides-Extra: tests
Requires-Dist: django
Requires-Dist: django-choices
Requires-Dist: django-filter (>=2.0)
Requires-Dist: djangorestframework-camel-case
Requires-Dist: drf-yasg
Requires-Dist: drf-nested-routers
Requires-Dist: gemma-zds-client (>=0.9.3)
Requires-Dist: iso-639
Requires-Dist: isodate
Requires-Dist: oyaml
Requires-Dist: PyJWT
Requires-Dist: pyyaml
Requires-Dist: requests
Requires-Dist: unidecode
Provides-Extra: coverage
Requires-Dist: pytest-cov; extra == 'coverage'
Provides-Extra: docs
Requires-Dist: sphinx; extra == 'docs'
Requires-Dist: sphinx-rtd-theme; extra == 'docs'
Provides-Extra: pep8
Requires-Dist: flake8; extra == 'pep8'
Provides-Extra: release
Requires-Dist: zest.releaser; extra == 'release'
Provides-Extra: tests
Requires-Dist: pytest; extra == 'tests'
Requires-Dist: pytest-django; extra == 'tests'
Requires-Dist: tox; extra == 'tests'
Requires-Dist: isort; extra == 'tests'
